gitfaces/__about__.py
gitfaces/__init__.py
gitfaces/cli.py
gitfaces/main.py
gitfaces-0.3.0.dist-info/LICENSE
gitfaces-0.3.0.dist-info/METADATA
gitfaces-0.3.0.dist-info/WHEEL
gitfaces-0.3.0.dist-info/entry_points.txt
gitfaces-0.3.0.dist-info/top_level.txt
gitfaces-0.3.0.dist-info/RECORD
