Metadata-Version: 2.1
Name: gitfaces
Version: 0.3.0
Summary: Fetch contributor avatars for a GitHub repository
Home-page: https://github.com/nschloe/gitfaces
Author: Nico Schlömer
Author-email: nico.schloemer@gmail.com
License: GPL-3.0-or-later
Project-URL: Code, https://github.com/nschloe/gitfaces
Project-URL: Issues, https://github.com/nschloe/gitfaces/issues
Platform: UNKNOWN
Classifier: Development Status :: 4 - Beta
Classifier: License :: OSI Approved :: GNU General Public License v3 or later (GPLv3+)
Classifier: Operating System :: OS Independent
Classifier: Programming Language :: Python
Classifier: Programming Language :: Python :: 3
Classifier: Programming Language :: Python :: 3.6
Classifier: Programming Language :: Python :: 3.7
Classifier: Programming Language :: Python :: 3.8
Classifier: Topic :: Multimedia :: Graphics
Classifier: Topic :: Software Development :: Version Control
Requires-Python: >=3.5
Requires-Dist: GitPython
Requires-Dist: Pillow
Requires-Dist: requests
Requires-Dist: importlib-metadata ; python_version < "3.8"
